[
  {
    "sortOrder": 1,
    "model": "LA206",
    "nameZh": "LA206",
    "nameEn": "LA206",
    "descZh": "双 6.5 寸全频线阵列音箱",
    "descEn": "Dual 6.5\" full-range line array",
    "detailZh": "双 6.5 寸全频线阵列音箱",
    "detailEn": "Dual 6.5\" full-range line array",
    "specsZh": "85Hz–20kHz | 250W/1000W | 120dB | 16Ω",
    "specsEn": "85Hz–20kHz | 250W/1000W | 120dB | 16Ω",
    "seriesZh": "LA 线阵列音箱",
    "seriesEn": "LA Line Array",
    "productLine": "la",
    "seriesGroup": "speaker",
    "category": "speaker",
    "image": "/images/product-1.svg",
    "gallery": [
      "/images/product-1.svg",
      "/images/product-2.svg"
    ]
  },
  {
    "sortOrder": 2,
    "model": "LA115S",
    "nameZh": "LA115S",
    "nameEn": "LA115S",
    "descZh": "单 15 寸线阵列超低音箱",
    "descEn": "Single 15\" line array subwoofer",
    "detailZh": "单 15 寸线阵列超低音箱",
    "detailEn": "Single 15\" line array subwoofer",
    "specsZh": "50Hz–20kHz | 800W/3200W | 130dB | 8Ω",
    "specsEn": "50Hz–20kHz | 800W/3200W | 130dB | 8Ω",
    "seriesZh": "LA 线阵列音箱",
    "seriesEn": "LA Line Array",
    "productLine": "la",
    "seriesGroup": "speaker",
    "category": "speaker",
    "image": "/images/product-2.svg",
    "gallery": [
      "/images/product-2.svg",
      "/images/product-3.svg"
    ]
  },
  {
    "sortOrder": 3,
    "model": "LA208",
    "nameZh": "LA208",
    "nameEn": "LA208",
    "descZh": "双 8 寸全频线阵列音箱",
    "descEn": "Dual 8\" full-range line array",
    "detailZh": "双 8 寸全频线阵列音箱",
    "detailEn": "Dual 8\" full-range line array",
    "specsZh": "80Hz–20kHz | 300W/1200W | 123dB | 8Ω",
    "specsEn": "80Hz–20kHz | 300W/1200W | 123dB | 8Ω",
    "seriesZh": "LA 线阵列音箱",
    "seriesEn": "LA Line Array",
    "productLine": "la",
    "seriesGroup": "speaker",
    "category": "speaker",
    "image": "/images/product-3.svg",
    "gallery": [
      "/images/product-3.svg",
      "/images/product-4.svg"
    ]
  },
  {
    "sortOrder": 4,
    "model": "LA118S",
    "nameZh": "LA118S",
    "nameEn": "LA118S",
    "descZh": "单 18 寸线阵列超低音箱",
    "descEn": "Single 18\" line array subwoofer",
    "detailZh": "单 18 寸线阵列超低音箱",
    "detailEn": "Single 18\" line array subwoofer",
    "specsZh": "50Hz–20kHz | 800W/3200W | 130dB | 8Ω",
    "specsEn": "50Hz–20kHz | 800W/3200W | 130dB | 8Ω",
    "seriesZh": "LA 线阵列音箱",
    "seriesEn": "LA Line Array",
    "productLine": "la",
    "seriesGroup": "speaker",
    "category": "speaker",
    "image": "/images/product-4.svg",
    "gallery": [
      "/images/product-4.svg",
      "/images/product-1.svg"
    ]
  },
  {
    "sortOrder": 5,
    "model": "LA210",
    "nameZh": "LA210",
    "nameEn": "LA210",
    "descZh": "双 10 寸全频线阵列音箱",
    "descEn": "Dual 10\" full-range line array",
    "detailZh": "双 10 寸全频线阵列音箱",
    "detailEn": "Dual 10\" full-range line array",
    "specsZh": "50Hz–20kHz | 800W/3200W | 130dB | 8Ω",
    "specsEn": "50Hz–20kHz | 800W/3200W | 130dB | 8Ω",
    "seriesZh": "LA 线阵列音箱",
    "seriesEn": "LA Line Array",
    "productLine": "la",
    "seriesGroup": "speaker",
    "category": "speaker",
    "image": "/images/product-1.svg",
    "gallery": [
      "/images/product-1.svg",
      "/images/product-2.svg"
    ]
  },
  {
    "sortOrder": 6,
    "model": "LA118W",
    "nameZh": "LA118W",
    "nameEn": "LA118W",
    "descZh": "单 18 寸线阵列超低音箱",
    "descEn": "Single 18\" line array subwoofer",
    "detailZh": "单 18 寸线阵列超低音箱",
    "detailEn": "Single 18\" line array subwoofer",
    "specsZh": "50Hz–20kHz | 800W/3200W | 130dB | 8Ω",
    "specsEn": "50Hz–20kHz | 800W/3200W | 130dB | 8Ω",
    "seriesZh": "LA 线阵列音箱",
    "seriesEn": "LA Line Array",
    "productLine": "la",
    "seriesGroup": "speaker",
    "category": "speaker",
    "image": "/images/product-2.svg",
    "gallery": [
      "/images/product-2.svg",
      "/images/product-3.svg"
    ]
  },
  {
    "sortOrder": 7,
    "model": "LA121W",
    "nameZh": "LA121W",
    "nameEn": "LA121W",
    "descZh": "单 21 寸线阵列超低音箱",
    "descEn": "Single 21\" line array subwoofer",
    "detailZh": "单 21 寸线阵列超低音箱",
    "detailEn": "Single 21\" line array subwoofer",
    "specsZh": "50Hz–20kHz | 800W/3200W | 130dB | 8Ω",
    "specsEn": "50Hz–20kHz | 800W/3200W | 130dB | 8Ω",
    "seriesZh": "LA 线阵列音箱",
    "seriesEn": "LA Line Array",
    "productLine": "la",
    "seriesGroup": "speaker",
    "category": "speaker",
    "image": "/images/product-3.svg",
    "gallery": [
      "/images/product-3.svg",
      "/images/product-4.svg"
    ]
  },
  {
    "sortOrder": 8,
    "model": "LA212",
    "nameZh": "LA212",
    "nameEn": "LA212",
    "descZh": "双 12 寸全频线阵列音箱",
    "descEn": "Dual 12\" full-range line array",
    "detailZh": "双 12 寸全频线阵列音箱",
    "detailEn": "Dual 12\" full-range line array",
    "specsZh": "50Hz–20kHz | 800W/3200W | 130dB | 8Ω",
    "specsEn": "50Hz–20kHz | 800W/3200W | 130dB | 8Ω",
    "seriesZh": "LA 线阵列音箱",
    "seriesEn": "LA Line Array",
    "productLine": "la",
    "seriesGroup": "speaker",
    "category": "speaker",
    "image": "/images/product-4.svg",
    "gallery": [
      "/images/product-4.svg",
      "/images/product-1.svg"
    ]
  },
  {
    "sortOrder": 9,
    "model": "LA218S",
    "nameZh": "LA218S",
    "nameEn": "LA218S",
    "descZh": "双 18 寸线阵列超低音箱",
    "descEn": "Dual 18\" line array subwoofer",
    "detailZh": "双 18 寸线阵列超低音箱",
    "detailEn": "Dual 18\" line array subwoofer",
    "specsZh": "50Hz–20kHz | 800W/3200W | 130dB | 8Ω",
    "specsEn": "50Hz–20kHz | 800W/3200W | 130dB | 8Ω",
    "seriesZh": "LA 线阵列音箱",
    "seriesEn": "LA Line Array",
    "productLine": "la",
    "seriesGroup": "speaker",
    "category": "speaker",
    "image": "/images/product-1.svg",
    "gallery": [
      "/images/product-1.svg",
      "/images/product-2.svg"
    ]
  },
  {
    "sortOrder": 10,
    "model": "LW210L",
    "nameZh": "LW210L",
    "nameEn": "LW210L",
    "descZh": "双 10 寸全天候线阵列音箱",
    "descEn": "Dual 10\" all-weather line array",
    "detailZh": "双 10 寸全天候线阵列音箱",
    "detailEn": "Dual 10\" all-weather line array",
    "specsZh": "75Hz–20kHz | 150W/600W | IP66",
    "specsEn": "75Hz–20kHz | 150W/600W | IP66",
    "seriesZh": "LW 中远程防水音箱",
    "seriesEn": "LW Medium-Throw IP",
    "productLine": "lw",
    "seriesGroup": "speaker",
    "category": "speaker",
    "image": "/images/product-2.svg",
    "gallery": [
      "/images/product-2.svg",
      "/images/product-3.svg"
    ]
  },
  {
    "sortOrder": 11,
    "model": "LW18S",
    "nameZh": "LW18S",
    "nameEn": "LW18S",
    "descZh": "单 18 寸全天候线阵列超低",
    "descEn": "Single 18\" all-weather line array sub",
    "detailZh": "单 18 寸全天候线阵列超低",
    "detailEn": "Single 18\" all-weather line array sub",
    "specsZh": "75Hz–20kHz | 150W/600W | IP66",
    "specsEn": "75Hz–20kHz | 150W/600W | IP66",
    "seriesZh": "LW 中远程防水音箱",
    "seriesEn": "LW Medium-Throw IP",
    "productLine": "lw",
    "seriesGroup": "speaker",
    "category": "speaker",
    "image": "/images/product-3.svg",
    "gallery": [
      "/images/product-3.svg",
      "/images/product-4.svg"
    ]
  },
  {
    "sortOrder": 12,
    "model": "LW6",
    "nameZh": "LW6",
    "nameEn": "LW6",
    "descZh": "6.5 寸全天候两分频音箱",
    "descEn": "6.5\" all-weather two-way speaker",
    "detailZh": "6.5 寸全天候两分频音箱",
    "detailEn": "6.5\" all-weather two-way speaker",
    "specsZh": "75Hz–20kHz | 150W/600W | IP66",
    "specsEn": "75Hz–20kHz | 150W/600W | IP66",
    "seriesZh": "LW 中远程防水音箱",
    "seriesEn": "LW Medium-Throw IP",
    "productLine": "lw",
    "seriesGroup": "speaker",
    "category": "speaker",
    "image": "/images/product-4.svg",
    "gallery": [
      "/images/product-4.svg",
      "/images/product-1.svg"
    ]
  },
  {
    "sortOrder": 13,
    "model": "LW8",
    "nameZh": "LW8",
    "nameEn": "LW8",
    "descZh": "8 寸全天候两分频音箱",
    "descEn": "8\" all-weather two-way speaker",
    "detailZh": "8 寸全天候两分频音箱",
    "detailEn": "8\" all-weather two-way speaker",
    "specsZh": "75Hz–20kHz | 150W/600W | IP66",
    "specsEn": "75Hz–20kHz | 150W/600W | IP66",
    "seriesZh": "LW 中远程防水音箱",
    "seriesEn": "LW Medium-Throw IP",
    "productLine": "lw",
    "seriesGroup": "speaker",
    "category": "speaker",
    "image": "/images/product-1.svg",
    "gallery": [
      "/images/product-1.svg",
      "/images/product-2.svg"
    ]
  },
  {
    "sortOrder": 14,
    "model": "LW12",
    "nameZh": "LW12",
    "nameEn": "LW12",
    "descZh": "12 寸全天候两分频音箱",
    "descEn": "12\" all-weather two-way speaker",
    "detailZh": "12 寸全天候两分频音箱",
    "detailEn": "12\" all-weather two-way speaker",
    "specsZh": "75Hz–20kHz | 150W/600W | IP66",
    "specsEn": "75Hz–20kHz | 150W/600W | IP66",
    "seriesZh": "LW 中远程防水音箱",
    "seriesEn": "LW Medium-Throw IP",
    "productLine": "lw",
    "seriesGroup": "speaker",
    "category": "speaker",
    "image": "/images/product-2.svg",
    "gallery": [
      "/images/product-2.svg",
      "/images/product-3.svg"
    ]
  },
  {
    "sortOrder": 15,
    "model": "LW15",
    "nameZh": "LW15",
    "nameEn": "LW15",
    "descZh": "15 寸全天候两分频音箱",
    "descEn": "15\" all-weather two-way speaker",
    "detailZh": "15 寸全天候两分频音箱",
    "detailEn": "15\" all-weather two-way speaker",
    "specsZh": "75Hz–20kHz | 150W/600W | IP66",
    "specsEn": "75Hz–20kHz | 150W/600W | IP66",
    "seriesZh": "LW 中远程防水音箱",
    "seriesEn": "LW Medium-Throw IP",
    "productLine": "lw",
    "seriesGroup": "speaker",
    "category": "speaker",
    "image": "/images/product-3.svg",
    "gallery": [
      "/images/product-3.svg",
      "/images/product-4.svg"
    ]
  },
  {
    "sortOrder": 16,
    "model": "LW208",
    "nameZh": "LW208",
    "nameEn": "LW208",
    "descZh": "8 寸同轴全天候中远程音箱",
    "descEn": "8\" coaxial all-weather mid-long range",
    "detailZh": "8 寸同轴全天候中远程音箱",
    "detailEn": "8\" coaxial all-weather mid-long range",
    "specsZh": "75Hz–20kHz | 150W/600W | IP66",
    "specsEn": "75Hz–20kHz | 150W/600W | IP66",
    "seriesZh": "LW 中远程防水音箱",
    "seriesEn": "LW Medium-Throw IP",
    "productLine": "lw",
    "seriesGroup": "speaker",
    "category": "speaker",
    "image": "/images/product-4.svg",
    "gallery": [
      "/images/product-4.svg",
      "/images/product-1.svg"
    ]
  },
  {
    "sortOrder": 17,
    "model": "LW212",
    "nameZh": "LW212",
    "nameEn": "LW212",
    "descZh": "12 寸同轴全天候中远程音箱",
    "descEn": "12\" coaxial all-weather mid-long range",
    "detailZh": "12 寸同轴全天候中远程音箱",
    "detailEn": "12\" coaxial all-weather mid-long range",
    "specsZh": "75Hz–20kHz | 150W/600W | IP66",
    "specsEn": "75Hz–20kHz | 150W/600W | IP66",
    "seriesZh": "LW 中远程防水音箱",
    "seriesEn": "LW Medium-Throw IP",
    "productLine": "lw",
    "seriesGroup": "speaker",
    "category": "speaker",
    "image": "/images/product-1.svg",
    "gallery": [
      "/images/product-1.svg",
      "/images/product-2.svg"
    ]
  },
  {
    "sortOrder": 18,
    "model": "LW215",
    "nameZh": "LW215",
    "nameEn": "LW215",
    "descZh": "15 寸同轴全天候中远程音箱",
    "descEn": "15\" coaxial all-weather mid-long range",
    "detailZh": "15 寸同轴全天候中远程音箱",
    "detailEn": "15\" coaxial all-weather mid-long range",
    "specsZh": "75Hz–20kHz | 150W/600W | IP66",
    "specsEn": "75Hz–20kHz | 150W/600W | IP66",
    "seriesZh": "LW 中远程防水音箱",
    "seriesEn": "LW Medium-Throw IP",
    "productLine": "lw",
    "seriesGroup": "speaker",
    "category": "speaker",
    "image": "/images/product-2.svg",
    "gallery": [
      "/images/product-2.svg",
      "/images/product-3.svg"
    ]
  },
  {
    "sortOrder": 19,
    "model": "MI12",
    "nameZh": "MI12",
    "nameEn": "MI12",
    "descZh": "12 寸同轴舞台返听音箱",
    "descEn": "12\" coaxial stage monitor",
    "detailZh": "12 寸同轴舞台返听音箱",
    "detailEn": "12\" coaxial stage monitor",
    "specsZh": "70Hz–20kHz | 300W/1200W | 122dB",
    "specsEn": "70Hz–20kHz | 300W/1200W | 122dB",
    "seriesZh": "MI 返送音箱",
    "seriesEn": "MI Stage Monitor",
    "productLine": "mi",
    "seriesGroup": "speaker",
    "category": "speaker",
    "image": "/images/product-3.svg",
    "gallery": [
      "/images/product-3.svg",
      "/images/product-4.svg"
    ]
  },
  {
    "sortOrder": 20,
    "model": "MI15",
    "nameZh": "MI15",
    "nameEn": "MI15",
    "descZh": "15 寸同轴舞台返听音箱",
    "descEn": "15\" coaxial stage monitor",
    "detailZh": "15 寸同轴舞台返听音箱",
    "detailEn": "15\" coaxial stage monitor",
    "specsZh": "70Hz–20kHz | 300W/1200W | 122dB",
    "specsEn": "70Hz–20kHz | 300W/1200W | 122dB",
    "seriesZh": "MI 返送音箱",
    "seriesEn": "MI Stage Monitor",
    "productLine": "mi",
    "seriesGroup": "speaker",
    "category": "speaker",
    "image": "/images/product-4.svg",
    "gallery": [
      "/images/product-4.svg",
      "/images/product-1.svg"
    ]
  },
  {
    "sortOrder": 21,
    "model": "DO106",
    "nameZh": "DO106",
    "nameEn": "DO106",
    "descZh": "6.5 寸两分频全频音箱",
    "descEn": "6.5\" two-way full-range speaker",
    "detailZh": "6.5 寸两分频全频音箱",
    "detailEn": "6.5\" two-way full-range speaker",
    "specsZh": "60Hz–20kHz | 300W/1200W | 122dB",
    "specsEn": "60Hz–20kHz | 300W/1200W | 122dB",
    "seriesZh": "DO 多功能全频音箱",
    "seriesEn": "DO Full-Range",
    "productLine": "do",
    "seriesGroup": "speaker",
    "category": "speaker",
    "image": "/images/product-1.svg",
    "gallery": [
      "/images/product-1.svg",
      "/images/product-2.svg"
    ]
  },
  {
    "sortOrder": 22,
    "model": "DO108",
    "nameZh": "DO108",
    "nameEn": "DO108",
    "descZh": "8 寸两分频全频音箱",
    "descEn": "8\" two-way full-range speaker",
    "detailZh": "8 寸两分频全频音箱",
    "detailEn": "8\" two-way full-range speaker",
    "specsZh": "60Hz–20kHz | 300W/1200W | 122dB",
    "specsEn": "60Hz–20kHz | 300W/1200W | 122dB",
    "seriesZh": "DO 多功能全频音箱",
    "seriesEn": "DO Full-Range",
    "productLine": "do",
    "seriesGroup": "speaker",
    "category": "speaker",
    "image": "/images/product-2.svg",
    "gallery": [
      "/images/product-2.svg",
      "/images/product-3.svg"
    ]
  },
  {
    "sortOrder": 23,
    "model": "DO110",
    "nameZh": "DO110",
    "nameEn": "DO110",
    "descZh": "10 寸两分频全频音箱",
    "descEn": "10\" two-way full-range speaker",
    "detailZh": "10 寸两分频全频音箱",
    "detailEn": "10\" two-way full-range speaker",
    "specsZh": "60Hz–20kHz | 300W/1200W | 122dB",
    "specsEn": "60Hz–20kHz | 300W/1200W | 122dB",
    "seriesZh": "DO 多功能全频音箱",
    "seriesEn": "DO Full-Range",
    "productLine": "do",
    "seriesGroup": "speaker",
    "category": "speaker",
    "image": "/images/product-3.svg",
    "gallery": [
      "/images/product-3.svg",
      "/images/product-4.svg"
    ]
  },
  {
    "sortOrder": 24,
    "model": "DO112",
    "nameZh": "DO112",
    "nameEn": "DO112",
    "descZh": "12 寸两分频全频音箱",
    "descEn": "12\" two-way full-range speaker",
    "detailZh": "12 寸两分频全频音箱",
    "detailEn": "12\" two-way full-range speaker",
    "specsZh": "60Hz–20kHz | 300W/1200W | 122dB",
    "specsEn": "60Hz–20kHz | 300W/1200W | 122dB",
    "seriesZh": "DO 多功能全频音箱",
    "seriesEn": "DO Full-Range",
    "productLine": "do",
    "seriesGroup": "speaker",
    "category": "speaker",
    "image": "/images/product-4.svg",
    "gallery": [
      "/images/product-4.svg",
      "/images/product-1.svg"
    ]
  },
  {
    "sortOrder": 25,
    "model": "DO115",
    "nameZh": "DO115",
    "nameEn": "DO115",
    "descZh": "15 寸两分频全频音箱",
    "descEn": "15\" two-way full-range speaker",
    "detailZh": "15 寸两分频全频音箱",
    "detailEn": "15\" two-way full-range speaker",
    "specsZh": "60Hz–20kHz | 300W/1200W | 122dB",
    "specsEn": "60Hz–20kHz | 300W/1200W | 122dB",
    "seriesZh": "DO 多功能全频音箱",
    "seriesEn": "DO Full-Range",
    "productLine": "do",
    "seriesGroup": "speaker",
    "category": "speaker",
    "image": "/images/product-1.svg",
    "gallery": [
      "/images/product-1.svg",
      "/images/product-2.svg"
    ]
  },
  {
    "sortOrder": 26,
    "model": "DO115H",
    "nameZh": "DO115H",
    "nameEn": "DO115H",
    "descZh": "15 寸高功率两分频全频音箱",
    "descEn": "15\" high-power two-way speaker",
    "detailZh": "15 寸高功率两分频全频音箱",
    "detailEn": "15\" high-power two-way speaker",
    "specsZh": "60Hz–20kHz | 300W/1200W | 122dB",
    "specsEn": "60Hz–20kHz | 300W/1200W | 122dB",
    "seriesZh": "DO 多功能全频音箱",
    "seriesEn": "DO Full-Range",
    "productLine": "do",
    "seriesGroup": "speaker",
    "category": "speaker",
    "image": "/images/product-2.svg",
    "gallery": [
      "/images/product-2.svg",
      "/images/product-3.svg"
    ]
  },
  {
    "sortOrder": 27,
    "model": "DO215",
    "nameZh": "DO215",
    "nameEn": "DO215",
    "descZh": "双 15 寸两分频全频音箱",
    "descEn": "Dual 15\" two-way full-range speaker",
    "detailZh": "双 15 寸两分频全频音箱",
    "detailEn": "Dual 15\" two-way full-range speaker",
    "specsZh": "60Hz–20kHz | 300W/1200W | 122dB",
    "specsEn": "60Hz–20kHz | 300W/1200W | 122dB",
    "seriesZh": "DO 多功能全频音箱",
    "seriesEn": "DO Full-Range",
    "productLine": "do",
    "seriesGroup": "speaker",
    "category": "speaker",
    "image": "/images/product-3.svg",
    "gallery": [
      "/images/product-3.svg",
      "/images/product-4.svg"
    ]
  },
  {
    "sortOrder": 28,
    "model": "DO115S",
    "nameZh": "DO115S",
    "nameEn": "DO115S",
    "descZh": "15 寸倒相式超低音箱",
    "descEn": "15\" inverted subwoofer",
    "detailZh": "15 寸倒相式超低音箱",
    "detailEn": "15\" inverted subwoofer",
    "specsZh": "60Hz–20kHz | 300W/1200W | 122dB",
    "specsEn": "60Hz–20kHz | 300W/1200W | 122dB",
    "seriesZh": "DO 多功能全频音箱",
    "seriesEn": "DO Full-Range",
    "productLine": "do",
    "seriesGroup": "speaker",
    "category": "speaker",
    "image": "/images/product-4.svg",
    "gallery": [
      "/images/product-4.svg",
      "/images/product-1.svg"
    ]
  },
  {
    "sortOrder": 29,
    "model": "DO118S",
    "nameZh": "DO118S",
    "nameEn": "DO118S",
    "descZh": "18 寸倒相式超低音箱",
    "descEn": "18\" inverted subwoofer",
    "detailZh": "18 寸倒相式超低音箱",
    "detailEn": "18\" inverted subwoofer",
    "specsZh": "60Hz–20kHz | 300W/1200W | 122dB",
    "specsEn": "60Hz–20kHz | 300W/1200W | 122dB",
    "seriesZh": "DO 多功能全频音箱",
    "seriesEn": "DO Full-Range",
    "productLine": "do",
    "seriesGroup": "speaker",
    "category": "speaker",
    "image": "/images/product-1.svg",
    "gallery": [
      "/images/product-1.svg",
      "/images/product-2.svg"
    ]
  },
  {
    "sortOrder": 30,
    "model": "DO218S",
    "nameZh": "DO218S",
    "nameEn": "DO218S",
    "descZh": "双 18 寸倒相式超低音箱",
    "descEn": "Dual 18\" inverted subwoofer",
    "detailZh": "双 18 寸倒相式超低音箱",
    "detailEn": "Dual 18\" inverted subwoofer",
    "specsZh": "60Hz–20kHz | 300W/1200W | 122dB",
    "specsEn": "60Hz–20kHz | 300W/1200W | 122dB",
    "seriesZh": "DO 多功能全频音箱",
    "seriesEn": "DO Full-Range",
    "productLine": "do",
    "seriesGroup": "speaker",
    "category": "speaker",
    "image": "/images/product-2.svg",
    "gallery": [
      "/images/product-2.svg",
      "/images/product-3.svg"
    ]
  },
  {
    "sortOrder": 31,
    "model": "SOL403",
    "nameZh": "SOL403",
    "nameEn": "SOL403",
    "descZh": "2×4 寸全天候音柱音箱",
    "descEn": "2×4\" all-weather column speaker",
    "detailZh": "2×4 寸全天候音柱音箱",
    "detailEn": "2×4\" all-weather column speaker",
    "specsZh": "120Hz–20kHz | 80W/320W | IP66",
    "specsEn": "120Hz–20kHz | 80W/320W | IP66",
    "seriesZh": "SOL 多功能防水音柱",
    "seriesEn": "SOL IP Column",
    "productLine": "sol",
    "seriesGroup": "speaker",
    "category": "speaker",
    "image": "/images/product-3.svg",
    "gallery": [
      "/images/product-3.svg",
      "/images/product-4.svg"
    ]
  },
  {
    "sortOrder": 32,
    "model": "SOL405",
    "nameZh": "SOL405",
    "nameEn": "SOL405",
    "descZh": "4×4 寸全天候音柱音箱",
    "descEn": "4×4\" all-weather column speaker",
    "detailZh": "4×4 寸全天候音柱音箱",
    "detailEn": "4×4\" all-weather column speaker",
    "specsZh": "120Hz–20kHz | 80W/320W | IP66",
    "specsEn": "120Hz–20kHz | 80W/320W | IP66",
    "seriesZh": "SOL 多功能防水音柱",
    "seriesEn": "SOL IP Column",
    "productLine": "sol",
    "seriesGroup": "speaker",
    "category": "speaker",
    "image": "/images/product-4.svg",
    "gallery": [
      "/images/product-4.svg",
      "/images/product-1.svg"
    ]
  },
  {
    "sortOrder": 33,
    "model": "SOL407",
    "nameZh": "SOL407",
    "nameEn": "SOL407",
    "descZh": "6×4 寸全天候音柱音箱",
    "descEn": "6×4\" all-weather column speaker",
    "detailZh": "6×4 寸全天候音柱音箱",
    "detailEn": "6×4\" all-weather column speaker",
    "specsZh": "120Hz–20kHz | 80W/320W | IP66",
    "specsEn": "120Hz–20kHz | 80W/320W | IP66",
    "seriesZh": "SOL 多功能防水音柱",
    "seriesEn": "SOL IP Column",
    "productLine": "sol",
    "seriesGroup": "speaker",
    "category": "speaker",
    "image": "/images/product-1.svg",
    "gallery": [
      "/images/product-1.svg",
      "/images/product-2.svg"
    ]
  },
  {
    "sortOrder": 34,
    "model": "K10",
    "nameZh": "K10",
    "nameEn": "K10",
    "descZh": "10 寸两分频娱乐音箱",
    "descEn": "10\" two-way entertainment speaker",
    "detailZh": "10 寸两分频娱乐音箱",
    "detailEn": "10\" two-way entertainment speaker",
    "specsZh": "45Hz–20kHz | 300W/1200W | 娱乐扩声",
    "specsEn": "45Hz–20kHz | 300W/1200W | entertainment PA",
    "seriesZh": "K 系列娱乐音箱",
    "seriesEn": "K Entertainment",
    "productLine": "k",
    "seriesGroup": "speaker",
    "category": "speaker",
    "image": "/images/product-2.svg",
    "gallery": [
      "/images/product-2.svg",
      "/images/product-3.svg"
    ]
  },
  {
    "sortOrder": 35,
    "model": "K12",
    "nameZh": "K12",
    "nameEn": "K12",
    "descZh": "12 寸两分频娱乐音箱",
    "descEn": "12\" two-way entertainment speaker",
    "detailZh": "12 寸两分频娱乐音箱",
    "detailEn": "12\" two-way entertainment speaker",
    "specsZh": "45Hz–20kHz | 300W/1200W | 122dB",
    "specsEn": "45Hz–20kHz | 300W/1200W | 122dB",
    "seriesZh": "K 系列娱乐音箱",
    "seriesEn": "K Entertainment",
    "productLine": "k",
    "seriesGroup": "speaker",
    "category": "speaker",
    "image": "/images/product-3.svg",
    "gallery": [
      "/images/product-3.svg",
      "/images/product-4.svg"
    ]
  },
  {
    "sortOrder": 36,
    "model": "K212S",
    "nameZh": "K212S",
    "nameEn": "K212S",
    "descZh": "双 12 寸倒相式超低音箱",
    "descEn": "Dual 12\" inverted subwoofer",
    "detailZh": "双 12 寸倒相式超低音箱",
    "detailEn": "Dual 12\" inverted subwoofer",
    "specsZh": "45Hz–20kHz | 300W/1200W | 娱乐扩声",
    "specsEn": "45Hz–20kHz | 300W/1200W | entertainment PA",
    "seriesZh": "K 系列娱乐音箱",
    "seriesEn": "K Entertainment",
    "productLine": "k",
    "seriesGroup": "speaker",
    "category": "speaker",
    "image": "/images/product-4.svg",
    "gallery": [
      "/images/product-4.svg",
      "/images/product-1.svg"
    ]
  },
  {
    "sortOrder": 37,
    "model": "K18S",
    "nameZh": "K18S",
    "nameEn": "K18S",
    "descZh": "单 18 寸倒相式超低音箱",
    "descEn": "18\" inverted subwoofer",
    "detailZh": "单 18 寸倒相式超低音箱",
    "detailEn": "18\" inverted subwoofer",
    "specsZh": "45Hz–20kHz | 300W/1200W | 娱乐扩声",
    "specsEn": "45Hz–20kHz | 300W/1200W | entertainment PA",
    "seriesZh": "K 系列娱乐音箱",
    "seriesEn": "K Entertainment",
    "productLine": "k",
    "seriesGroup": "speaker",
    "category": "speaker",
    "image": "/images/product-1.svg",
    "gallery": [
      "/images/product-1.svg",
      "/images/product-2.svg"
    ]
  },
  {
    "sortOrder": 38,
    "model": "RE8",
    "nameZh": "RE8",
    "nameEn": "RE8",
    "descZh": "8 寸两分频全频音箱",
    "descEn": "8\" two-way full-range speaker",
    "detailZh": "8 寸两分频全频音箱",
    "detailEn": "8\" two-way full-range speaker",
    "specsZh": "45Hz–20kHz | 250W/1000W | 会议全频",
    "specsEn": "45Hz–20kHz | 250W/1000W | conference full-range",
    "seriesZh": "RE 全频音箱",
    "seriesEn": "RE Full-Range",
    "productLine": "re",
    "seriesGroup": "speaker",
    "category": "speaker",
    "image": "/images/product-2.svg",
    "gallery": [
      "/images/product-2.svg",
      "/images/product-3.svg"
    ]
  },
  {
    "sortOrder": 39,
    "model": "RE10",
    "nameZh": "RE10",
    "nameEn": "RE10",
    "descZh": "10 寸两分频全频音箱",
    "descEn": "10\" two-way full-range speaker",
    "detailZh": "10 寸两分频全频音箱",
    "detailEn": "10\" two-way full-range speaker",
    "specsZh": "45Hz–20kHz | 250W/1000W | 会议全频",
    "specsEn": "45Hz–20kHz | 250W/1000W | conference full-range",
    "seriesZh": "RE 全频音箱",
    "seriesEn": "RE Full-Range",
    "productLine": "re",
    "seriesGroup": "speaker",
    "category": "speaker",
    "image": "/images/product-3.svg",
    "gallery": [
      "/images/product-3.svg",
      "/images/product-4.svg"
    ]
  },
  {
    "sortOrder": 40,
    "model": "RE12",
    "nameZh": "RE12",
    "nameEn": "RE12",
    "descZh": "12 寸两分频全频音箱",
    "descEn": "12\" two-way full-range speaker",
    "detailZh": "12 寸两分频全频音箱",
    "detailEn": "12\" two-way full-range speaker",
    "specsZh": "45Hz–20kHz | 250W/1000W | 120dB",
    "specsEn": "45Hz–20kHz | 250W/1000W | 120dB",
    "seriesZh": "RE 全频音箱",
    "seriesEn": "RE Full-Range",
    "productLine": "re",
    "seriesGroup": "speaker",
    "category": "speaker",
    "image": "/images/product-4.svg",
    "gallery": [
      "/images/product-4.svg",
      "/images/product-1.svg"
    ]
  },
  {
    "sortOrder": 41,
    "model": "RE15",
    "nameZh": "RE15",
    "nameEn": "RE15",
    "descZh": "15 寸两分频全频音箱",
    "descEn": "15\" two-way full-range speaker",
    "detailZh": "15 寸两分频全频音箱",
    "detailEn": "15\" two-way full-range speaker",
    "specsZh": "45Hz–20kHz | 250W/1000W | 会议全频",
    "specsEn": "45Hz–20kHz | 250W/1000W | conference full-range",
    "seriesZh": "RE 全频音箱",
    "seriesEn": "RE Full-Range",
    "productLine": "re",
    "seriesGroup": "speaker",
    "category": "speaker",
    "image": "/images/product-1.svg",
    "gallery": [
      "/images/product-1.svg",
      "/images/product-2.svg"
    ]
  },
  {
    "sortOrder": 42,
    "model": "V12",
    "nameZh": "V12",
    "nameEn": "V12",
    "descZh": "单 12 寸线阵列音箱，搭配 V18",
    "descEn": "Single 12\" line array, pairs with V18",
    "detailZh": "单 12 寸线阵列音箱，搭配 V18",
    "detailEn": "Single 12\" line array, pairs with V18",
    "specsZh": "60Hz–18kHz | 400W/1600W | IP65 | 搭配 V18",
    "specsEn": "60Hz–18kHz | 400W/1600W | IP65 | with V18",
    "seriesZh": "流动演出系统",
    "seriesEn": "Touring Systems",
    "productLine": "tour",
    "seriesGroup": "speaker",
    "category": "speaker",
    "image": "/images/product-2.svg",
    "gallery": [
      "/images/product-2.svg",
      "/images/product-3.svg"
    ]
  },
  {
    "sortOrder": 43,
    "model": "V18",
    "nameZh": "V18",
    "nameEn": "V18",
    "descZh": "单 18 寸线阵列超低音箱",
    "descEn": "Single 18\" line array subwoofer",
    "detailZh": "单 18 寸线阵列超低音箱",
    "detailEn": "Single 18\" line array subwoofer",
    "specsZh": "32–300Hz | 600W/2400W | IP65",
    "specsEn": "32–300Hz | 600W/2400W | IP65",
    "seriesZh": "流动演出系统",
    "seriesEn": "Touring Systems",
    "productLine": "tour",
    "seriesGroup": "speaker",
    "category": "speaker",
    "image": "/images/product-3.svg",
    "gallery": [
      "/images/product-3.svg",
      "/images/product-4.svg"
    ]
  },
  {
    "sortOrder": 44,
    "model": "V212",
    "nameZh": "V212",
    "nameEn": "V212",
    "descZh": "三频线阵列音箱，搭配 V221S",
    "descEn": "3-way line array, pairs with V221S",
    "detailZh": "三频线阵列音箱，搭配 V221S",
    "detailEn": "3-way line array, pairs with V221S",
    "specsZh": "60Hz–18kHz | 三频线阵 | 搭配 V221S",
    "specsEn": "60Hz–18kHz | 3-way line array | with V221S",
    "seriesZh": "流动演出系统",
    "seriesEn": "Touring Systems",
    "productLine": "tour",
    "seriesGroup": "speaker",
    "category": "speaker",
    "image": "/images/product-4.svg",
    "gallery": [
      "/images/product-4.svg",
      "/images/product-1.svg"
    ]
  },
  {
    "sortOrder": 45,
    "model": "V221S",
    "nameZh": "V221S",
    "nameEn": "V221S",
    "descZh": "双 21 寸线阵列超低音箱",
    "descEn": "Dual 21\" line array subwoofer",
    "detailZh": "双 21 寸线阵列超低音箱",
    "detailEn": "Dual 21\" line array subwoofer",
    "specsZh": "25–150Hz | 1600W/6400W | IP65",
    "specsEn": "25–150Hz | 1600W/6400W | IP65",
    "seriesZh": "流动演出系统",
    "seriesEn": "Touring Systems",
    "productLine": "tour",
    "seriesGroup": "speaker",
    "category": "speaker",
    "image": "/images/product-1.svg",
    "gallery": [
      "/images/product-1.svg",
      "/images/product-2.svg"
    ]
  },
  {
    "sortOrder": 46,
    "model": "VIT",
    "nameZh": "VIT 系统",
    "nameEn": "VIT System",
    "descZh": "V12×8 + V18×6 + V415A×2 标准配置",
    "descEn": "V12×8 + V18×6 + V415A×2 standard kit",
    "detailZh": "V12×8 + V18×6 + V415A×2 标准配置",
    "detailEn": "V12×8 + V18×6 + V415A×2 standard kit",
    "specsZh": "V12×8 + V18×6 + V415A×2 标准配置",
    "specsEn": "V12×8 + V18×6 + V415A×2 standard kit",
    "seriesZh": "流动演出系统",
    "seriesEn": "Touring Systems",
    "productLine": "tour",
    "seriesGroup": "speaker",
    "category": "speaker",
    "image": "/images/product-2.svg",
    "gallery": [
      "/images/product-2.svg",
      "/images/product-3.svg"
    ]
  },
  {
    "sortOrder": 47,
    "model": "206M",
    "nameZh": "206M",
    "nameEn": "206M",
    "descZh": "舞台返听音箱",
    "descEn": "Stage monitor speaker",
    "detailZh": "舞台返听音箱",
    "detailEn": "Stage monitor speaker",
    "specsZh": "90Hz–20kHz | 280W/1120W | 116dB",
    "specsEn": "90Hz–20kHz | 280W/1120W | 116dB",
    "seriesZh": "流动演出系统",
    "seriesEn": "Touring Systems",
    "productLine": "tour",
    "seriesGroup": "speaker",
    "category": "speaker",
    "image": "/images/product-3.svg",
    "gallery": [
      "/images/product-3.svg",
      "/images/product-4.svg"
    ]
  },
  {
    "sortOrder": 48,
    "model": "15N",
    "nameZh": "15N",
    "nameEn": "15N",
    "descZh": "流动演出全频音箱",
    "descEn": "Touring full-range speaker",
    "detailZh": "流动演出全频音箱",
    "detailEn": "Touring full-range speaker",
    "specsZh": "60Hz–18kHz | 400W/1600W | IP65 | 搭配 V18",
    "specsEn": "60Hz–18kHz | 400W/1600W | IP65 | with V18",
    "seriesZh": "流动演出系统",
    "seriesEn": "Touring Systems",
    "productLine": "tour",
    "seriesGroup": "speaker",
    "category": "speaker",
    "image": "/images/product-4.svg",
    "gallery": [
      "/images/product-4.svg",
      "/images/product-1.svg"
    ]
  },
  {
    "sortOrder": 49,
    "model": "Solo C",
    "nameZh": "Solo C",
    "nameEn": "Solo C",
    "descZh": "演出现场控台监听音箱",
    "descEn": "FOH console monitor speaker",
    "detailZh": "演出现场控台监听音箱",
    "detailEn": "FOH console monitor speaker",
    "specsZh": "60Hz–18kHz | 400W/1600W | IP65 | 搭配 V18",
    "specsEn": "60Hz–18kHz | 400W/1600W | IP65 | with V18",
    "seriesZh": "流动演出系统",
    "seriesEn": "Touring Systems",
    "productLine": "tour",
    "seriesGroup": "speaker",
    "category": "speaker",
    "image": "/images/product-1.svg",
    "gallery": [
      "/images/product-1.svg",
      "/images/product-2.svg"
    ]
  },
  {
    "sortOrder": 50,
    "model": "V4",
    "nameZh": "V4 音柱",
    "nameEn": "V4 Column",
    "descZh": "有源音柱系统",
    "descEn": "Powered column system",
    "detailZh": "有源音柱系统",
    "detailEn": "Powered column system",
    "specsZh": "60Hz–18kHz | 400W/1600W | IP65 | 搭配 V18",
    "specsEn": "60Hz–18kHz | 400W/1600W | IP65 | with V18",
    "seriesZh": "流动演出系统",
    "seriesEn": "Touring Systems",
    "productLine": "tour",
    "seriesGroup": "speaker",
    "category": "speaker",
    "image": "/images/product-2.svg",
    "gallery": [
      "/images/product-2.svg",
      "/images/product-3.svg"
    ]
  },
  {
    "sortOrder": 51,
    "model": "V4SA",
    "nameZh": "V4SA 超低",
    "nameEn": "V4SA Sub",
    "descZh": "有源音柱超低模块",
    "descEn": "Powered column sub module",
    "detailZh": "有源音柱超低模块",
    "detailEn": "Powered column sub module",
    "specsZh": "60Hz–18kHz | 400W/1600W | IP65 | 搭配 V18",
    "specsEn": "60Hz–18kHz | 400W/1600W | IP65 | with V18",
    "seriesZh": "流动演出系统",
    "seriesEn": "Touring Systems",
    "productLine": "tour",
    "seriesGroup": "speaker",
    "category": "speaker",
    "image": "/images/product-3.svg",
    "gallery": [
      "/images/product-3.svg",
      "/images/product-4.svg"
    ]
  },
  {
    "sortOrder": 52,
    "model": "V415A",
    "nameZh": "V415A",
    "nameEn": "V415A",
    "descZh": "4 通道 DSP 功放机柜",
    "descEn": "4-channel DSP amplifier rack",
    "detailZh": "4 通道 DSP 功放机柜",
    "detailEn": "4-channel DSP amplifier rack",
    "specsZh": "4×1500W@8Ω | Dante | DSP",
    "specsEn": "4×1500W@8Ω | Dante | DSP",
    "seriesZh": "电子产品",
    "seriesEn": "Electronics",
    "productLine": "electronics",
    "seriesGroup": "speaker",
    "category": "speaker",
    "image": "/images/product-4.svg",
    "gallery": [
      "/images/product-4.svg",
      "/images/product-1.svg"
    ]
  },
  {
    "sortOrder": 53,
    "model": "V225A",
    "nameZh": "V225A",
    "nameEn": "V225A",
    "descZh": "2 通道 DSP 功放",
    "descEn": "2-channel DSP amplifier",
    "detailZh": "2 通道 DSP 功放",
    "detailEn": "2-channel DSP amplifier",
    "specsZh": "2×2500W@4Ω | Dante | DSP",
    "specsEn": "2×2500W@4Ω | Dante | DSP",
    "seriesZh": "电子产品",
    "seriesEn": "Electronics",
    "productLine": "electronics",
    "seriesGroup": "speaker",
    "category": "speaker",
    "image": "/images/product-1.svg",
    "gallery": [
      "/images/product-1.svg",
      "/images/product-2.svg"
    ]
  },
  {
    "sortOrder": 54,
    "model": "Unit48",
    "nameZh": "Unit48",
    "nameEn": "Unit48",
    "descZh": "音频处理器 / 音箱管理器",
    "descEn": "Audio processor / loudspeaker manager",
    "detailZh": "音频处理器 / 音箱管理器",
    "detailEn": "Audio processor / loudspeaker manager",
    "specsZh": "96kHz | 123dB 动态范围 | Dante",
    "specsEn": "96kHz | 123dB dynamic range | Dante",
    "seriesZh": "unit48 系列",
    "seriesEn": "unit48 Series",
    "productLine": "unit48",
    "seriesGroup": "dsp",
    "category": "dsp",
    "image": "/images/product-2.svg",
    "gallery": [
      "/images/product-2.svg",
      "/images/product-3.svg"
    ]
  },
  {
    "sortOrder": 55,
    "model": "dBcover",
    "nameZh": "dBcover",
    "nameEn": "dBcover",
    "descZh": "声学模拟与系统设计软件",
    "descEn": "Acoustic simulation & design software",
    "detailZh": "声学模拟与系统设计软件",
    "detailEn": "Acoustic simulation & design software",
    "specsZh": "Win / macOS 声学模拟",
    "specsEn": "Win / macOS acoustic simulation",
    "seriesZh": "dBcover 软件",
    "seriesEn": "dBcover Software",
    "productLine": "suite",
    "seriesGroup": "software",
    "category": "software",
    "image": "/images/product-3.svg",
    "gallery": [
      "/images/product-3.svg",
      "/images/product-4.svg"
    ]
  }
]